django_backblaze_b2/__init__.py
django_backblaze_b2/_decorators.py
django_backblaze_b2/b2_file.py
django_backblaze_b2/cache_account_info.py
django_backblaze_b2/options.py
django_backblaze_b2/py.typed
django_backblaze_b2/storage.py
django_backblaze_b2/storages.py
django_backblaze_b2/urls.py
django_backblaze_b2/views.py
django_backblaze_b2-6.0.2.dist-info/LICENSE
django_backblaze_b2-6.0.2.dist-info/METADATA
django_backblaze_b2-6.0.2.dist-info/WHEEL
django_backblaze_b2-6.0.2.dist-info/RECORD
