Metadata-Version: 2.1
Name: django-backblaze-b2
Version: 6.0.2
Summary: A Django app to use backblaze b2 as storage.
Home-page: https://github.com/ehossack/django-backblaze-b2/
License: BSD-2-Clause
Keywords: django,storage,backblaze,b2,cloud
Author: Etienne H
Author-email: django_backblaze_b2@internet-e-mail.com
Maintainer: Etienne H
Maintainer-email: django_backblaze_b2@internet-e-mail.com
Requires-Python: >=3.8.1,<4.0.0
Classifier: Development Status :: 5 - Production/Stable
Classifier: Environment :: Web Environment
Classifier: Framework :: Django
Classifier: Framework :: Django :: 3.2
Classifier: Framework :: Django :: 4.2
Classifier: Framework :: Django :: 5.0
Classifier: Framework :: Django :: 5.1
Classifier: Intended Audience :: Developers
Classifier: License :: OSI Approved :: BSD License
Classifier: Operating System :: OS Independent
Classifier: Programming Language :: Python
Classifier: Programming Language :: Python :: 3
Classifier: Programming Language :: Python :: 3.9
Classifier: Programming Language :: Python :: 3.10
Classifier: Programming Language :: Python :: 3.11
Classifier: Programming Language :: Python :: 3.12
Classifier: Programming Language :: Python :: 3 :: Only
Classifier: Programming Language :: Python :: 3.8
Classifier: Topic :: Software Development :: Libraries :: Application Frameworks
Classifier: Topic :: Software Development :: Libraries :: Python Modules
Classifier: Typing :: Typed
Requires-Dist: b2sdk (>=2.0.0,<3.0.0)
Requires-Dist: django (>=3.2)
Requires-Dist: typing-extensions (>=4.0.1,<5.0.0)
Project-URL: Repository, https://github.com/ehossack/django-backblaze-b2/
